ispyb_dja/__init__.py
ispyb_dja/manage.py
ispyb_dja/django_auth/__init__.py
ispyb_dja/django_auth/admin.py
ispyb_dja/django_auth/models.py
ispyb_dja/django_auth/serializers.py
ispyb_dja/django_auth/settings.py
ispyb_dja/django_auth/urls.py
ispyb_dja/django_auth/views.py
ispyb_dja/django_auth/wsgi.py
ispyb_dja/django_auth/migrations/0001_initial.py
ispyb_dja/django_auth/migrations/__init__.py
ispyb_dja/ispyb_auth/__init__.py
ispyb_dja/ispyb_auth/ispyb_djangoauth.py
ispyb_dja/ispyb_auth/ispyb_remote_connector.py
ispyb_dja/tests/__init__.py
ispyb_dja/tests/test_api.py
ispyb_dja-1.0.1.dist-info/METADATA
ispyb_dja-1.0.1.dist-info/WHEEL
ispyb_dja-1.0.1.dist-info/entry_points.txt
ispyb_dja-1.0.1.dist-info/top_level.txt
ispyb_dja-1.0.1.dist-info/RECORD
